skdr_eval/__init__.py
skdr_eval/_version.py
skdr_eval/choice.py
skdr_eval/core.py
skdr_eval/pairwise.py
skdr_eval/synth.py
skdr_eval-0.4.2.dist-info/licenses/LICENSE
skdr_eval-0.4.2.dist-info/METADATA
skdr_eval-0.4.2.dist-info/WHEEL
skdr_eval-0.4.2.dist-info/top_level.txt
skdr_eval-0.4.2.dist-info/RECORD
