Metadata-Version: 2.4
Name: skdr-eval
Version: 0.4.2
Summary: Offline policy evaluation for service-time minimization using DR and Stabilized DR
Author-email: Diogo Santos <diogofcul@gmail.com>
License: MIT
Project-URL: Homepage, https://github.com/dandrsantos/skdr-eval
Project-URL: Repository, https://github.com/dandrsantos/skdr-eval
Project-URL: Issues, https://github.com/dandrsantos/skdr-eval/issues
Keywords: offline evaluation,doubly robust,bandits,causal
Classifier: Development Status :: 4 - Beta
Classifier: Intended Audience :: Science/Research
Classifier: License :: OSI Approved :: MIT License
Classifier: Programming Language :: Python :: 3
Classifier: Programming Language :: Python :: 3 :: Only
Classifier: Programming Language :: Python :: 3.9
Classifier: Programming Language :: Python :: 3.10
Classifier: Programming Language :: Python :: 3.11
Classifier: Programming Language :: Python :: 3.12
Classifier: Topic :: Scientific/Engineering
Classifier: Topic :: Scientific/Engineering :: Artificial Intelligence
Requires-Python: >=3.9
License-File: LICENSE
Requires-Dist: numpy
Requires-Dist: pandas
Requires-Dist: scikit-learn>=1.1
Provides-Extra: choice
Requires-Dist: scipy>=1.9; extra == "choice"
Provides-Extra: speed
Requires-Dist: pyarrow>=14; extra == "speed"
Requires-Dist: polars>=0.20; extra == "speed"
Provides-Extra: dev
Requires-Dist: pytest; extra == "dev"
Requires-Dist: pytest-cov; extra == "dev"
Requires-Dist: coverage; extra == "dev"
Requires-Dist: mypy; extra == "dev"
Requires-Dist: ruff; extra == "dev"
Requires-Dist: black; extra == "dev"
Requires-Dist: build; extra == "dev"
Requires-Dist: twine; extra == "dev"
Requires-Dist: pre-commit; extra == "dev"
Provides-Extra: examples
Requires-Dist: jupyter; extra == "examples"
Requires-Dist: matplotlib; extra == "examples"
Dynamic: license-file
